area/__init__.py
area/shapes.py
codersao-1.1.dist-info/METADATA
codersao-1.1.dist-info/WHEEL
codersao-1.1.dist-info/top_level.txt
codersao-1.1.dist-info/RECORD
