Metadata-Version: 2.4
Name: codersao
Version: 1.1
Summary: A simple library to calculate area of shapes
Author: Jatin Ghoyal
Author-email: codersao@gmail.com
Dynamic: author
Dynamic: author-email
Dynamic: summary
